brainglobe_atlasapi/__init__.py
brainglobe_atlasapi/bg_atlas.py
brainglobe_atlasapi/cli.py
brainglobe_atlasapi/config.py
brainglobe_atlasapi/core.py
brainglobe_atlasapi/descriptors.py
brainglobe_atlasapi/list_atlases.py
brainglobe_atlasapi/structure_class.py
brainglobe_atlasapi/structure_tree_util.py
brainglobe_atlasapi/update_atlases.py
brainglobe_atlasapi/utils.py
brainglobe_atlasapi/atlas_generation/__init__.py
brainglobe_atlasapi/atlas_generation/annotation_utils.py
brainglobe_atlasapi/atlas_generation/mesh_utils.py
brainglobe_atlasapi/atlas_generation/metadata_utils.py
brainglobe_atlasapi/atlas_generation/stacks.py
brainglobe_atlasapi/atlas_generation/structure_json_to_csv.py
brainglobe_atlasapi/atlas_generation/structures.py
brainglobe_atlasapi/atlas_generation/validate_atlases.py
brainglobe_atlasapi/atlas_generation/volume_utils.py
brainglobe_atlasapi/atlas_generation/wrapup.py
brainglobe_atlasapi/atlas_generation/atlas_scripts/__init__.py
brainglobe_atlasapi/atlas_generation/atlas_scripts/admba_3d_dev_mouse.py
brainglobe_atlasapi/atlas_generation/atlas_scripts/allen_bbp_ccfv3a_entire_mouse_brain.py
brainglobe_atlasapi/atlas_generation/atlas_scripts/allen_cord.py
brainglobe_atlasapi/atlas_generation/atlas_scripts/allen_human.py
brainglobe_atlasapi/atlas_generation/atlas_scripts/allen_mouse.py
brainglobe_atlasapi/atlas_generation/atlas_scripts/allen_mouse_bluebrain_barrels.py
brainglobe_atlasapi/atlas_generation/atlas_scripts/australian_mouse.py
brainglobe_atlasapi/atlas_generation/atlas_scripts/azba_zfish.py
brainglobe_atlasapi/atlas_generation/atlas_scripts/ccfv3augmented_mouse.py
brainglobe_atlasapi/atlas_generation/atlas_scripts/columbia_cuttlefish.py
brainglobe_atlasapi/atlas_generation/atlas_scripts/csl_cat.py
brainglobe_atlasapi/atlas_generation/atlas_scripts/drosophila_wingdisc_instar3.py
brainglobe_atlasapi/atlas_generation/atlas_scripts/eurasian_blackcap.py
brainglobe_atlasapi/atlas_generation/atlas_scripts/example_mouse.py
brainglobe_atlasapi-2.3.0.dist-info/licenses/LICENSE
brainglobe_atlasapi-2.3.0.dist-info/METADATA
brainglobe_atlasapi-2.3.0.dist-info/WHEEL
brainglobe_atlasapi-2.3.0.dist-info/entry_points.txt
brainglobe_atlasapi-2.3.0.dist-info/top_level.txt
brainglobe_atlasapi-2.3.0.dist-info/RECORD
