Metadata-Version: 2.4
Name: brainglobe-atlasapi
Version: 2.3.0
Summary: A lightweight python module to interact with and generate atlases for systems neuroscience.
Author-email: "Luigi Petrucco, Federico Claudi, Adam Tyson" <code@adamltyson.com>
License: BSD 3-Clause License
Project-URL: Homepage, https://brainglobe.info/documentation/brainglobe-atlasapi/index.html
Project-URL: Source Code, https://github.com/brainglobe/brainglobe-atlasapi
Project-URL: Bug Tracker, https://github.com/brainglobe/brainglobe-atlasapi/issues
Project-URL: Documentation, https://brainglobe.info/documentation/brainglobe-atlasapi/index.html
Classifier: Development Status :: 3 - Alpha
Classifier: Intended Audience :: Developers
Classifier: Intended Audience :: Science/Research
Classifier: Operating System :: OS Independent
Classifier: Programming Language :: Python
Classifier: Programming Language :: Python :: 3
Classifier: Programming Language :: Python :: 3.11
Classifier: Programming Language :: Python :: 3.12
Classifier: Programming Language :: Python :: 3.13
Requires-Python: >=3.11
License-File: LICENSE
Requires-Dist: brainglobe-space>=1.0.0
Requires-Dist: click
Requires-Dist: meshio
Requires-Dist: numpy
Requires-Dist: pandas
Requires-Dist: pyarrow
Requires-Dist: requests
Requires-Dist: rich>=9.0.0
Requires-Dist: tifffile>=2018.11.6
Requires-Dist: treelib
Provides-Extra: dev
Requires-Dist: black; extra == "dev"
Requires-Dist: check-manifest; extra == "dev"
Requires-Dist: coverage; extra == "dev"
Requires-Dist: mypy; extra == "dev"
Requires-Dist: pre-commit; extra == "dev"
Requires-Dist: pytest-cov; extra == "dev"
Requires-Dist: pytest-mock; extra == "dev"
Requires-Dist: pytest; extra == "dev"
Requires-Dist: ruff; extra == "dev"
Requires-Dist: setuptools_scm; extra == "dev"
Requires-Dist: tox; extra == "dev"
Provides-Extra: allenmouse
Requires-Dist: allensdk; extra == "allenmouse"
Provides-Extra: allenmouse-barrels
Requires-Dist: allensdk; extra == "allenmouse-barrels"
Requires-Dist: voxcell; extra == "allenmouse-barrels"
Provides-Extra: perens-stereotaxic-mri-mouse
Requires-Dist: py7zr; extra == "perens-stereotaxic-mri-mouse"
Provides-Extra: kocher-bumblebee
Requires-Dist: vtk; extra == "kocher-bumblebee"
Provides-Extra: atlasgen
Requires-Dist: loguru; extra == "atlasgen"
Requires-Dist: PyMCubes; extra == "atlasgen"
Requires-Dist: SimpleITK; extra == "atlasgen"
Requires-Dist: tqdm>=4.46.1; extra == "atlasgen"
Requires-Dist: vedo; extra == "atlasgen"
Requires-Dist: xmltodict; extra == "atlasgen"
Requires-Dist: brainglobe-utils; extra == "atlasgen"
Requires-Dist: pooch; extra == "atlasgen"
Dynamic: license-file
